phagecommander/Gene.py
phagecommander/__init__.py
phagecommander/phagecom.py
phagecommander/species.txt
phagecommander/GuiWidgets/ProdigalDialogue.py
phagecommander/GuiWidgets/RastJobDialogue.py
phagecommander/GuiWidgets/__init__.py
phagecommander/GuiWidgets/exportDialogue.py
phagecommander/Utilities/MetagenePy.py
phagecommander/Utilities/ProdigalRelease.py
phagecommander/Utilities/QueryData.py
phagecommander/Utilities/RastPy.py
phagecommander/Utilities/ThreadData.py
phagecommander/Utilities/__init__.py
phage_commander-0.4.5.dev0.dist-info/LICENSE
phage_commander-0.4.5.dev0.dist-info/METADATA
phage_commander-0.4.5.dev0.dist-info/WHEEL
phage_commander-0.4.5.dev0.dist-info/entry_points.txt
phage_commander-0.4.5.dev0.dist-info/top_level.txt
phage_commander-0.4.5.dev0.dist-info/RECORD
