Metadata-Version: 2.1
Name: phage-commander
Version: 0.4.5.dev0
Summary: A graphical tool for predicting genes on phage DNA sequences
Home-page: https://github.com/mlazeroff/PhageCommander
Author: Matthew Lazeroff
Author-email: lazeroff@unlv.nevada.edu
License: GPL-3
Platform: UNKNOWN
Classifier: Programming Language :: Python :: 3
Classifier: License :: OSI Approved :: GNU General Public License v3 (GPLv3)
Classifier: Operating System :: Microsoft :: Windows
Classifier: Operating System :: MacOS
Classifier: Operating System :: Unix
Requires-Dist: requests
Requires-Dist: bs4
Requires-Dist: openpyxl
Requires-Dist: pyqt5
Requires-Dist: biopython
Requires-Dist: ruamel.yaml
